config.py
downloader.py
main.py
utils.py
image_curator-0.1.0.dist-info/licenses/LICENSE
image_sources/__init__.py
image_sources/flickr.py
image_curator-0.1.0.dist-info/METADATA
image_curator-0.1.0.dist-info/WHEEL
image_curator-0.1.0.dist-info/entry_points.txt
image_curator-0.1.0.dist-info/top_level.txt
image_curator-0.1.0.dist-info/RECORD
