Metadata-Version: 2.4
Name: image-curator
Version: 0.1.0
Summary: A production-ready Python tool for curating and downloading images from multiple sources
Author-email: ghostcipher1 <ghostcipher1@users.noreply.github.com>
Maintainer-email: ghostcipher1 <ghostcipher1@users.noreply.github.com>
License-Expression: MIT
Project-URL: Homepage, https://github.com/ghostcipher1/image-curator
Project-URL: Documentation, https://github.com/ghostcipher1/image-curator#readme
Project-URL: Repository, https://github.com/ghostcipher1/image-curator
Project-URL: Issues, https://github.com/ghostcipher1/image-curator/issues
Project-URL: Changelog, https://github.com/ghostcipher1/image-curator/releases
Keywords: image-downloader,flickr,api-client,creative-commons,web-scraping,automation,dataset-collection,computer-vision,machine-learning
Classifier: Development Status :: 4 - Beta
Classifier: Intended Audience :: Developers
Classifier: Intended Audience :: Science/Research
Classifier: Operating System :: OS Independent
Classifier: Programming Language :: Python :: 3
Classifier: Programming Language :: Python :: 3.8
Classifier: Programming Language :: Python :: 3.9
Classifier: Programming Language :: Python :: 3.10
Classifier: Programming Language :: Python :: 3.11
Classifier: Programming Language :: Python :: 3.12
Classifier: Topic :: Multimedia :: Graphics
Classifier: Topic :: Scientific/Engineering :: Image Processing
Classifier: Topic :: Software Development :: Libraries :: Python Modules
Classifier: Topic :: Utilities
Requires-Python: >=3.8
License-File: LICENSE
Requires-Dist: requests>=2.32.0
Requires-Dist: python-dotenv>=1.0.0
Requires-Dist: tenacity>=8.2.0
Requires-Dist: tqdm>=4.66.0
Provides-Extra: dev
Requires-Dist: pytest>=8.0.0; extra == "dev"
Requires-Dist: pytest-cov>=4.1.0; extra == "dev"
Requires-Dist: ruff>=0.1.0; extra == "dev"
Requires-Dist: black>=23.0.0; extra == "dev"
Requires-Dist: mypy>=1.7.0; extra == "dev"
Dynamic: license-file
